{
    "network-name": "happy-testnet",
    "rpc-url": "https://happy-testnet-sepolia.rpc.caldera.xyz/http",
    "min-entity-stake": 1,
    "min-executor-balance": "1000000000000000000",
    "min-entity-unstake-delay": 1,
    "max-bundle-wait": 3,
    "max-bundle-size": 3,
    "max-block-range": 500,
    "port": 49531,
    "entrypoints": "0x0000000071727De22E5E9d8BAf0edAc6f37da032",
    "entrypoint-simulation-contract": "0x74Cb5e4eE81b86e70f9045036a1C5477de69eE87",
    "enable-debug-endpoints": true,
    "safe-mode": false,
    "mempool-max-parallel-ops": 5,
    "mempool-max-queued-ops": 5,
    "enforce-unique-senders-per-bundle": false
}
